collectfast/__init__.py
collectfast/py.typed
collectfast/settings.py
collectfast/management/__init__.py
collectfast/management/commands/__init__.py
collectfast/management/commands/collectstatic.py
collectfast/strategies/__init__.py
collectfast/strategies/base.py
collectfast/strategies/boto3.py
collectfast/strategies/filesystem.py
collectfast/strategies/gcloud.py
collectfast/tests/__init__.py
collectfast/tests/settings.py
collectfast/tests/test_settings.py
collectfast/tests/utils.py
collectfast/tests/command/__init__.py
collectfast/tests/command/test_command.py
collectfast/tests/command/test_disable.py
collectfast/tests/command/test_post_process.py
collectfast/tests/command/utils.py
collectfast/tests/strategies/__init__.py
collectfast/tests/strategies/test_caching_hash_strategy.py
collectfast/tests/strategies/test_hash_strategy.py
Collectfast-2.1.0.dist-info/LICENSE
Collectfast-2.1.0.dist-info/METADATA
Collectfast-2.1.0.dist-info/WHEEL
Collectfast-2.1.0.dist-info/top_level.txt
Collectfast-2.1.0.dist-info/RECORD
