Metadata-Version: 2.1
Name: Collectfast
Version: 2.1.0
Summary: A Faster Collectstatic
Home-page: https://github.com/antonagestam/collectfast/
Author: Anton Agestam
Author-email: git@antonagestam.se
License: MIT License
Platform: UNKNOWN
Classifier: Environment :: Web Environment
Classifier: Intended Audience :: Developers
Classifier: Operating System :: OS Independent
Classifier: Programming Language :: Python
Classifier: Programming Language :: Python :: 3
Classifier: Programming Language :: Python :: 3.6
Classifier: Programming Language :: Python :: 3.7
Classifier: Programming Language :: Python :: 3.8
Classifier: Framework :: Django
Requires-Python: >=3.6
